exfunc_agent_toolkit/__init__.py
exfunc_agent_toolkit/api.py
exfunc_agent_toolkit/prompts.py
exfunc_agent_toolkit/schema.py
exfunc_agent_toolkit/tools.py
exfunc_agent_toolkit/langchain/tool.py
exfunc_agent_toolkit/langchain/toolkit.py
exfunc_agent_toolkit-0.0.2.dist-info/licenses/LICENSE
exfunc_agent_toolkit-0.0.2.dist-info/METADATA
exfunc_agent_toolkit-0.0.2.dist-info/WHEEL
exfunc_agent_toolkit-0.0.2.dist-info/top_level.txt
exfunc_agent_toolkit-0.0.2.dist-info/RECORD
