Metadata-Version: 2.4
Name: exfunc-agent-toolkit
Version: 0.0.2
Summary: Exfunc Agent Toolkit
Author-email: Exfunc <support@carvedai.com>
License: The MIT License (MIT)
Project-URL: Bug Tracker, https://github.com/carvedai/exfunc-agent-toolkit/issues
Project-URL: Source Code, https://github.com/carvedai/exfunc-agent-toolkit
Keywords: exfunc,api,automation
License-File: LICENSE
Dynamic: license-file
